ffmpy3.py
ffmpy3-0.2.3.dist-info/DESCRIPTION.rst
ffmpy3-0.2.3.dist-info/METADATA
ffmpy3-0.2.3.dist-info/RECORD
ffmpy3-0.2.3.dist-info/WHEEL
ffmpy3-0.2.3.dist-info/metadata.json
ffmpy3-0.2.3.dist-info/top_level.txt
