Metadata-Version: 1.1
Name: ffmpy3
Version: 0.2.3
Summary: A simple asynchronous Python wrapper for ffmpeg
Home-page: https://github.com/wchill/ffmpy3
Author: Eric Ahn
Author-email: ericahn3@illinois.edu
License: MIT
Keywords: ffmpeg ffprobe wrapper audio video transcoding
Platform: UNKNOWN
Classifier: Topic :: Multimedia :: Sound/Audio
Classifier: Development Status :: 4 - Beta
Classifier: Intended Audience :: Developers
Classifier: License :: OSI Approved :: MIT License
Classifier: Natural Language :: English
Classifier: Programming Language :: Python :: 3
Classifier: Programming Language :: Python :: 3.4
Classifier: Programming Language :: Python :: 3.5
Classifier: Programming Language :: Python :: Implementation :: CPython
Classifier: Operating System :: Microsoft :: Windows
Classifier: Operating System :: POSIX
Classifier: Operating System :: POSIX :: BSD
Classifier: Operating System :: POSIX :: Linux
Classifier: Operating System :: MacOS :: MacOS X
